netcdfkit/__init__.py
netcdfkit/logger.py
netcdfkit/point_extractor.py
netcdfkit/polygon_extractor.py
netcdfkit-0.1.2.dist-info/METADATA
netcdfkit-0.1.2.dist-info/WHEEL
netcdfkit-0.1.2.dist-info/licenses/LICENSE
netcdfkit-0.1.2.dist-info/RECORD
