Metadata-Version: 2.4
Name: netcdfkit
Version: 0.1.2
Summary: High-Performance NetCDF Data Extraction Toolkit for Climate and Environmental Sciences
Project-URL: Homepage, https://github.com/MuhammadShafeeque/netcdfkit
Project-URL: Documentation, https://github.com/MuhammadShafeeque/netcdfkit/tree/main/examples
Project-URL: Repository, https://github.com/MuhammadShafeeque/netcdfkit.git
Project-URL: Issues, https://github.com/MuhammadShafeeque/netcdfkit/issues
Project-URL: Changelog, https://github.com/MuhammadShafeeque/netcdfkit/releases
Author-email: Muhammad Shafeeque <muhammad.shafeeque@awi.de>
Maintainer-email: Muhammad Shafeeque <muhammad.shafeeque@awi.de>
License: MIT
License-File: LICENSE
Keywords: atmospheric-science,climate,data-extraction,earth-science,environmental,geospatial,meteorology,netcdf,spatial-analysis,time-series
Classifier: Development Status :: 4 - Beta
Classifier: Intended Audience :: Science/Research
Classifier: License :: OSI Approved :: MIT License
Classifier: Operating System :: OS Independent
Classifier: Programming Language :: Python :: 3
Classifier: Programming Language :: Python :: 3.12
Classifier: Topic :: Scientific/Engineering :: Atmospheric Science
Classifier: Topic :: Scientific/Engineering :: GIS
Classifier: Topic :: Scientific/Engineering :: Information Analysis
Classifier: Topic :: Software Development :: Libraries :: Python Modules
Requires-Python: >=3.12
Requires-Dist: build>=1.2.2.post1
Requires-Dist: bumpver>=2024.1130
Requires-Dist: dask>=2024.1.0
Requires-Dist: folium>=0.19.7
Requires-Dist: geopandas>=0.14.0
Requires-Dist: h5netcdf>=1.6.1
Requires-Dist: jupyter>=1.1.1
Requires-Dist: matplotlib>=3.10.3
Requires-Dist: numpy>=1.24.0
Requires-Dist: pandas>=2.0.0
Requires-Dist: pyarrow>=10.0.0
Requires-Dist: pyproj>=3.6.0
Requires-Dist: rasterio>=1.3.0
Requires-Dist: regionmask>=0.12.0
Requires-Dist: ruff>=0.11.13
Requires-Dist: scikit-learn>=1.3.0
Requires-Dist: seaborn>=0.13.2
Requires-Dist: shapely>=2.0.0
Requires-Dist: tqdm>=4.65.0
Requires-Dist: twine>=6.1.0
Requires-Dist: xarray>=2023.1.0
Provides-Extra: all
Requires-Dist: black>=23.0.0; extra == 'all'
Requires-Dist: folium>=0.14.0; extra == 'all'
Requires-Dist: jupyter>=1.0.0; extra == 'all'
Requires-Dist: matplotlib>=3.7.0; extra == 'all'
Requires-Dist: mypy>=1.5.0; extra == 'all'
Requires-Dist: pytest-cov>=4.0.0; extra == 'all'
Requires-Dist: pytest>=7.0.0; extra == 'all'
Requires-Dist: ruff>=0.1.0; extra == 'all'
Requires-Dist: seaborn>=0.12.0; extra == 'all'
Provides-Extra: dev
Requires-Dist: black>=23.0.0; extra == 'dev'
Requires-Dist: jupyter>=1.0.0; extra == 'dev'
Requires-Dist: mypy>=1.5.0; extra == 'dev'
Requires-Dist: pytest-cov>=4.0.0; extra == 'dev'
Requires-Dist: pytest>=7.0.0; extra == 'dev'
Requires-Dist: ruff>=0.1.0; extra == 'dev'
Provides-Extra: viz
Requires-Dist: folium>=0.14.0; extra == 'viz'
Requires-Dist: matplotlib>=3.7.0; extra == 'viz'
Requires-Dist: seaborn>=0.12.0; extra == 'viz'
